Metadata-Version: 1.0
Name: seun01-distributions
Version: 0.1
Summary: Gaussian distributions
Home-page: UNKNOWN
Author: Aboderin Samuel
Author-email: UNKNOWN
License: UNKNOWN
Platform: UNKNOWN
